MANIFEST.in
README
setup.py
smospy/J_Cord_to_tiff.py
smospy/J_Waveform.py
smospy/J_wavestream.py
smospy/__init__.py
smospy/smos_tools.py
smospy.egg-info/PKG-INFO
smospy.egg-info/SOURCES.txt
smospy.egg-info/dependency_links.txt
smospy.egg-info/entry_points.txt
smospy.egg-info/top_level.txt
smospy/c_functions/01_signal_c.cpp
smospy/c_functions/02_signal_c.h
smospy/c_functions/03_signal_c.cpp
smospy/c_functions/03_signal_c.pyx
smospy/c_functions/04_setup.py
smospy/c_functions/icbm_test.py