Metadata-Version: 2.1
Name: smospy
Version: 0.17
Summary: strong motion seismic data analysis module for Python
Home-page: https://gitext.gfz-potsdam.de/alejaege/smospy
Author: Alexander Jaeger
Author-email: Alexander@jaeger-erfurt.de
License: MIT
Keywords: seismology, waveform analysis,geophysics, geophysical inversion
Platform: UNKNOWN
Classifier: Development Status :: 3 - Alpha
Classifier: Intended Audience :: Science/Research
Classifier: License :: OSI Approved :: MIT License
Classifier: Programming Language :: Python :: 3
Classifier: Programming Language :: Cython
Classifier: Programming Language :: C++
Classifier: Topic :: Scientific/Engineering
Classifier: Topic :: Scientific/Engineering :: Physics
Requires-Python: >=3
